multicaller/__init__.py
multicaller/abi/multicall3.json
multicaller/multicaller.py
open_multicaller-0.3.7.dist-info/METADATA
open_multicaller-0.3.7.dist-info/WHEEL
open_multicaller-0.3.7.dist-info/RECORD
