Metadata-Version: 2.3
Name: open-multicaller
Version: 0.3.7
Summary: web3py multicaller simplified interface
Author: gerrrg
Author-email: gerrrrrrrg@gmail.com
Requires-Python: >=3.8.1,<4
Classifier: Programming Language :: Python :: 3
Classifier: Programming Language :: Python :: 3.9
Classifier: Programming Language :: Python :: 3.10
Classifier: Programming Language :: Python :: 3.11
Classifier: Programming Language :: Python :: 3.12
Classifier: Programming Language :: Python :: 3.13
Requires-Dist: web3 (>=6.0.0,<=9)
